{
  "version": "2.3.5",
  "flags": {},
  "shapes": [
    {
      "label": "DAIGHI DANEDAR HALEEM 293GX36 LOCAL",
      "points": [
        [
          766.1396789550781,
          435.00404357910156
        ],
        [
          879.8812866210938,
          435.00404357910156
        ],
        [
          879.8812866210938,
          537.8397369384766
        ],
        [
          766.1396789550781,
          537.8397369384766
        ]
      ],
      "group_id": null,
      "description": null,
      "difficult": false,
      "shape_type": "rectangle",
      "flags": {},
      "attributes": {}
    },
    {
      "label": "DAIGHI DANEDAR HALEEM 293GX36 LOCAL",
      "points": [
        [
          881.8875122070312,
          429.2925262451172
        ],
        [
          996.5492248535156,
          429.2925262451172
        ],
        [
          996.5492248535156,
          535.2777862548828
        ],
        [
          881.8875122070312,
          535.2777862548828
        ]
      ],
      "group_id": null,
      "description": null,
      "difficult": false,
      "shape_type": "rectangle",
      "flags": {},
      "attributes": {}
    },
    {
      "label": "Delhi Nihari 50GM (L)",
      "points": [
        [
          796.1705017089844,
          975.4646301269531
        ],
        [
          877.1180725097656,
          975.4646301269531
        ],
        [
          877.1180725097656,
          1046.8370056152344
        ],
        [
          796.1705017089844,
          1046.8370056152344
        ]
      ],
      "group_id": null,
      "description": null,
      "difficult": false,
      "shape_type": "rectangle",
      "flags": {},
      "attributes": {}
    },
    {
      "label": "BOMBAY BIRYANI 140G X 72 (KK)",
      "points": [
        [
          525.8524322509766,
          707.7857971191406
        ],
        [
          615.3763580322266,
          707.7857971191406
        ],
        [
          615.3763580322266,
          793.7965393066406
        ],
        [
          525.8524322509766,
          793.7965393066406
        ]
      ],
      "group_id": null,
      "description": null,
      "difficult": false,
      "shape_type": "rectangle",
      "flags": {},
      "attributes": {}
    },
    {
      "label": "Delhi Nihari 50GM (KK)",
      "points": [
        [
          704.1683959960938,
          725.3607177734375
        ],
        [
          777.3092651367188,
          725.3607177734375
        ],
        [
          777.3092651367188,
          795.7257080078125
        ],
        [
          704.1683959960938,
          795.7257080078125
        ]
      ],
      "group_id": null,
      "description": null,
      "difficult": false,
      "shape_type": "rectangle",
      "flags": {},
      "attributes": {}
    },
    {
      "label": "Delhi Nihari 50GM (KK)",
      "points": [
        [
          777.9081726074219,
          726.5300750732422
        ],
        [
          852.0823669433594,
          726.5300750732422
        ],
        [
          852.0823669433594,
          796.7877960205078
        ],
        [
          777.9081726074219,
          796.7877960205078
        ]
      ],
      "group_id": null,
      "description": null,
      "difficult": false,
      "shape_type": "rectangle",
      "flags": {},
      "attributes": {}
    },
    {
      "label": "BOMBAY BIRYANI 140G X 72 (KK)",
      "points": [
        [
          437.31964111328125,
          707.423095703125
        ],
        [
          526.6215515136719,
          707.423095703125
        ],
        [
          526.6215515136719,
          793.05908203125
        ],
        [
          437.31964111328125,
          793.05908203125
        ]
      ],
      "group_id": null,
      "description": null,
      "difficult": false,
      "shape_type": "rectangle",
      "flags": {},
      "attributes": {}
    },
    {
      "label": "TANDOORI MASALA 40GX72 (H)",
      "points": [
        [
          459.7151184082031,
          1253.2789611816406
        ],
        [
          539.1020202636719,
          1253.2789611816406
        ],
        [
          539.1020202636719,
          1344.2436218261719
        ],
        [
          459.7151184082031,
          1344.2436218261719
        ]
      ],
      "group_id": null,
      "description": null,
      "difficult": false,
      "shape_type": "rectangle",
      "flags": {},
      "attributes": {}
    },
    {
      "label": "Karahi Gosht 100GM (KK)",
      "points": [
        [
          579.95849609375,
          463.98292541503906
        ],
        [
          667.6335144042969,
          463.98292541503906
        ],
        [
          667.6335144042969,
          538.8297271728516
        ],
        [
          579.95849609375,
          538.8297271728516
        ]
      ],
      "group_id": null,
      "description": null,
      "difficult": false,
      "shape_type": "rectangle",
      "flags": {},
      "attributes": {}
    },
    {
      "label": "SEEKH KABAB 46GX72 (H)",
      "points": [
        [
          539.7405624389648,
          1257.5564575195312
        ],
        [
          624.3224716186523,
          1257.5564575195312
        ],
        [
          624.3224716186523,
          1348.98681640625
        ],
        [
          539.7405624389648,
          1348.98681640625
        ]
      ],
      "group_id": null,
      "description": null,
      "difficult": false,
      "shape_type": "rectangle",
      "flags": {},
      "attributes": {}
    },
    {
      "label": "Karahi Gosht 100GM (KK)",
      "points": [
        [
          491.9312286376953,
          461.5831756591797
        ],
        [
          579.7042846679688,
          461.5831756591797
        ],
        [
          579.7042846679688,
          537.6842498779297
        ],
        [
          491.9312286376953,
          537.6842498779297
        ]
      ],
      "group_id": null,
      "description": null,
      "difficult": false,
      "shape_type": "rectangle",
      "flags": {},
      "attributes": {}
    },
    {
      "label": "Delhi Nihari 50GM (L)",
      "points": [
        [
          716.015625,
          973.2571411132812
        ],
        [
          795.3082275390625,
          973.2571411132812
        ],
        [
          795.3082275390625,
          1045.0567626953125
        ],
        [
          716.015625,
          1045.0567626953125
        ]
      ],
      "group_id": null,
      "description": null,
      "difficult": false,
      "shape_type": "rectangle",
      "flags": {},
      "attributes": {}
    },
    {
      "label": "SEEKH KABAB 46GX72 (H)",
      "points": [
        [
          378.69972229003906,
          1248.3670043945312
        ],
        [
          458.85032653808594,
          1248.3670043945312
        ],
        [
          458.85032653808594,
          1339.6746826171875
        ],
        [
          378.69972229003906,
          1339.6746826171875
        ]
      ],
      "group_id": null,
      "description": null,
      "difficult": false,
      "shape_type": "rectangle",
      "flags": {},
      "attributes": {}
    },
    {
      "label": "HALEEM MASALA 43GX72 (H)",
      "points": [
        [
          997.6858520507812,
          467.7651596069336
        ],
        [
          1075.0079345703125,
          467.7651596069336
        ],
        [
          1075.0079345703125,
          531.2796401977539
        ],
        [
          997.6858520507812,
          531.2796401977539
        ]
      ],
      "group_id": null,
      "description": null,
      "difficult": false,
      "shape_type": "rectangle",
      "flags": {},
      "attributes": {}
    },
    {
      "label": "Delhi Nihari 50GM (KK)",
      "points": [
        [
          853.0731201171875,
          726.4791107177734
        ],
        [
          926.9580078125,
          726.4791107177734
        ],
        [
          926.9580078125,
          796.6967010498047
        ],
        [
          853.0731201171875,
          796.6967010498047
        ]
      ],
      "group_id": null,
      "description": null,
      "difficult": false,
      "shape_type": "rectangle",
      "flags": {},
      "attributes": {}
    },
    {
      "label": "Karahi Gosht 50GM (KK)",
      "points": [
        [
          556.7927169799805,
          970.7272338867188
        ],
        [
          634.9848556518555,
          970.7272338867188
        ],
        [
          634.9848556518555,
          1042.7093505859375
        ],
        [
          556.7927169799805,
          1042.7093505859375
        ]
      ],
      "group_id": null,
      "description": null,
      "difficult": false,
      "shape_type": "rectangle",
      "flags": {},
      "attributes": {}
    },
    {
      "label": "Quorma 100GM (KK)",
      "points": [
        [
          405.1255798339844,
          448.5881042480469
        ],
        [
          491.9383239746094,
          448.5881042480469
        ],
        [
          491.9383239746094,
          539.1029357910156
        ],
        [
          405.1255798339844,
          539.1029357910156
        ]
      ],
      "group_id": null,
      "description": null,
      "difficult": false,
      "shape_type": "rectangle",
      "flags": {},
      "attributes": {}
    },
    {
      "label": "YAKHNI PULAO 140GX72(H)",
      "points": [
        [
          350.07652282714844,
          703.7454223632812
        ],
        [
          437.73155212402344,
          703.7454223632812
        ],
        [
          437.73155212402344,
          789.4839477539062
        ],
        [
          350.07652282714844,
          789.4839477539062
        ]
      ],
      "group_id": null,
      "description": null,
      "difficult": false,
      "shape_type": "rectangle",
      "flags": {},
      "attributes": {}
    },
    {
      "label": "TIKKA BOTI MASALA 44GX72 (H)",
      "points": [
        [
          298.1781196594238,
          1245.1422119140625
        ],
        [
          378.260498046875,
          1245.1422119140625
        ],
        [
          378.260498046875,
          1335.73486328125
        ],
        [
          298.1781196594238,
          1335.73486328125
        ]
      ],
      "group_id": null,
      "description": null,
      "difficult": false,
      "shape_type": "rectangle",
      "flags": {},
      "attributes": {}
    },
    {
      "label": "TANDOORI MASALA 40GX72 (H)",
      "points": [
        [
          488.93699645996094,
          1144.6517944335938
        ],
        [
          556.5219116210938,
          1144.6517944335938
        ],
        [
          556.5219116210938,
          1248.438720703125
        ],
        [
          488.93699645996094,
          1248.438720703125
        ]
      ],
      "group_id": null,
      "description": null,
      "difficult": false,
      "shape_type": "rectangle",
      "flags": {},
      "attributes": {}
    },
    {
      "label": "BOMBAY BIRYANI 70G X 144 (KK)",
      "points": [
        [
          478.27247619628906,
          967.9154968261719
        ],
        [
          556.6487121582031,
          967.9154968261719
        ],
        [
          556.6487121582031,
          1041.8310546875
        ],
        [
          478.27247619628906,
          1041.8310546875
        ]
      ],
      "group_id": null,
      "description": null,
      "difficult": false,
      "shape_type": "rectangle",
      "flags": {},
      "attributes": {}
    },
    {
      "label": "PAYA MASALA 39GX72 (H)",
      "points": [
        [
          1080.4463808379905,
          1280.8898012481468
        ],
        [
          1169.9950258575218,
          1280.8898012481468
        ],
        [
          1169.9950258575218,
          1378.7938539825218
        ],
        [
          1080.4463808379905,
          1378.7938539825218
        ]
      ],
      "group_id": null,
      "description": null,
      "difficult": false,
      "shape_type": "rectangle",
      "flags": {},
      "attributes": {}
    },
    {
      "label": "HALEEM MASALA 43GX72 (H)",
      "points": [
        [
          1001.9500732421875,
          427.72605895996094
        ],
        [
          1081.7103576660156,
          427.72605895996094
        ],
        [
          1081.7103576660156,
          446.18988037109375
        ],
        [
          1001.9500732421875,
          446.18988037109375
        ]
      ],
      "group_id": null,
      "description": null,
      "difficult": false,
      "shape_type": "rectangle",
      "flags": {},
      "attributes": {}
    },
    {
      "label": "Delhi Nihari 100GM (KK)",
      "points": [
        [
          668.3598327636719,
          460.10108947753906
        ],
        [
          761.63818359375,
          460.10108947753906
        ],
        [
          761.63818359375,
          538.5187530517578
        ],
        [
          668.3598327636719,
          538.5187530517578
        ]
      ],
      "group_id": null,
      "description": null,
      "difficult": false,
      "shape_type": "rectangle",
      "flags": {},
      "attributes": {}
    },
    {
      "label": "HALEEM MASALA 43GX72 (H)",
      "points": [
        [
          1000.5385589599609,
          445.8793640136719
        ],
        [
          1080.580825805664,
          445.8793640136719
        ],
        [
          1080.580825805664,
          466.0536193847656
        ],
        [
          1000.5385589599609,
          466.0536193847656
        ]
      ],
      "group_id": null,
      "description": null,
      "difficult": false,
      "shape_type": "rectangle",
      "flags": {},
      "attributes": {}
    },
    {
      "label": "DAIGHI DANEDAR HALEEM 293GX36 LOCAL",
      "points": [
        [
          896.2841796875,
          360.78479766845703
        ],
        [
          1007.398681640625,
          360.78479766845703
        ],
        [
          1007.398681640625,
          391.4028549194336
        ],
        [
          896.2841796875,
          391.4028549194336
        ]
      ],
      "group_id": null,
      "description": null,
      "difficult": false,
      "shape_type": "rectangle",
      "flags": {},
      "attributes": {}
    },
    {
      "label": "DAIGHI DANEDAR HALEEM 293GX36 LOCAL",
      "points": [
        [
          892.55615234375,
          394.1301727294922
        ],
        [
          1003.6662292480469,
          394.1301727294922
        ],
        [
          1003.6662292480469,
          423.83323669433594
        ],
        [
          892.55615234375,
          423.83323669433594
        ]
      ],
      "group_id": null,
      "description": null,
      "difficult": false,
      "shape_type": "rectangle",
      "flags": {},
      "attributes": {}
    },
    {
      "label": "Delhi Nihari 50GM (L)",
      "points": [
        [
          635.1060104370117,
          970.6184387207031
        ],
        [
          714.7193908691406,
          970.6184387207031
        ],
        [
          714.7193908691406,
          1043.9009094238281
        ],
        [
          635.1060104370117,
          1043.9009094238281
        ]
      ],
      "group_id": null,
      "description": null,
      "difficult": false,
      "shape_type": "rectangle",
      "flags": {},
      "attributes": {}
    },
    {
      "label": "Achar Gosht 50GM (L)",
      "points": [
        [
          401.9530487060547,
          967.9280090332031
        ],
        [
          478.2294464111328,
          967.9280090332031
        ],
        [
          478.2294464111328,
          1039.5375061035156
        ],
        [
          401.9530487060547,
          1039.5375061035156
        ]
      ],
      "group_id": null,
      "description": null,
      "difficult": false,
      "shape_type": "rectangle",
      "flags": {},
      "attributes": {}
    },
    {
      "label": "CHAPLI KABAB 72GX72 (H)",
      "points": [
        [
          822.6524353027344,
          1210.8346557617188
        ],
        [
          906.5678405761719,
          1210.8346557617188
        ],
        [
          906.5678405761719,
          1238.4124755859375
        ],
        [
          822.6524353027344,
          1238.4124755859375
        ]
      ],
      "group_id": null,
      "description": "",
      "difficult": false,
      "shape_type": "rectangle",
      "flags": {},
      "attributes": {}
    },
    {
      "label": "Karahi Gosht 100GM (KK)",
      "points": [
        [
          494.9522018432617,
          440.428466796875
        ],
        [
          579.5137405395508,
          440.428466796875
        ],
        [
          579.5137405395508,
          459.91455078125
        ],
        [
          494.9522018432617,
          459.91455078125
        ]
      ],
      "group_id": null,
      "description": null,
      "difficult": false,
      "shape_type": "rectangle",
      "flags": {},
      "attributes": {}
    },
    {
      "label": "SHAMI KABAB 45GX72 (H)",
      "points": [
        [
          826.3453674316406,
          1158.5224914550781
        ],
        [
          905.9770202636719,
          1158.5224914550781
        ],
        [
          905.9770202636719,
          1207.2953796386719
        ],
        [
          826.3453674316406,
          1207.2953796386719
        ]
      ],
      "group_id": null,
      "description": null,
      "difficult": false,
      "shape_type": "rectangle",
      "flags": {},
      "attributes": {}
    },
    {
      "label": "Quorma 100GM (KK)",
      "points": [
        [
          618.4615384615385,
          705.3846153846154
        ],
        [
          706.1538461538461,
          705.3846153846154
        ],
        [
          706.1538461538461,
          791.5384615384615
        ],
        [
          618.4615384615385,
          791.5384615384615
        ]
      ],
      "group_id": null,
      "description": "",
      "difficult": false,
      "shape_type": "rectangle",
      "flags": {},
      "attributes": {}
    },
    {
      "label": "MURGHI MASALA 43GX144 (H)",
      "points": [
        [
          878.9473684210525,
          976.315789473684
        ],
        [
          962.2807017543859,
          976.315789473684
        ],
        [
          962.2807017543859,
          1048.2456140350876
        ],
        [
          878.9473684210525,
          1048.2456140350876
        ]
      ],
      "group_id": null,
      "description": "",
      "difficult": false,
      "shape_type": "rectangle",
      "flags": {},
      "attributes": {}
    },
    {
      "label": "MURGHI MASALA 43GX144 (H)",
      "points": [
        [
          963.157894736842,
          979.8245614035087
        ],
        [
          1046.491228070175,
          979.8245614035087
        ],
        [
          1046.491228070175,
          1051.7543859649122
        ],
        [
          963.157894736842,
          1051.7543859649122
        ]
      ],
      "group_id": null,
      "description": "",
      "difficult": false,
      "shape_type": "rectangle",
      "flags": {},
      "attributes": {}
    },
    {
      "label": "MURGHI MASALA 43GX144 (H)",
      "points": [
        [
          1048.2456140350876,
          982.456140350877
        ],
        [
          1131.5789473684206,
          982.456140350877
        ],
        [
          1131.5789473684206,
          1054.3859649122805
        ],
        [
          1048.2456140350876,
          1054.3859649122805
        ]
      ],
      "group_id": null,
      "description": "",
      "difficult": false,
      "shape_type": "rectangle",
      "flags": {},
      "attributes": {}
    },
    {
      "label": "MURGHI MASALA 43GX144 (H)",
      "points": [
        [
          1044.7368421052631,
          958.7719298245613
        ],
        [
          1129.8245614035086,
          958.7719298245613
        ],
        [
          1129.8245614035086,
          976.315789473684
        ],
        [
          1044.7368421052631,
          976.315789473684
        ]
      ],
      "group_id": null,
      "description": "",
      "difficult": false,
      "shape_type": "rectangle",
      "flags": {},
      "attributes": {}
    },
    {
      "label": "MURGHI MASALA 43GX144 (H)",
      "points": [
        [
          1045.6140350877192,
          936.8421052631578
        ],
        [
          1130.7017543859647,
          936.8421052631578
        ],
        [
          1130.7017543859647,
          954.3859649122805
        ],
        [
          1045.6140350877192,
          954.3859649122805
        ]
      ],
      "group_id": null,
      "description": "",
      "difficult": false,
      "shape_type": "rectangle",
      "flags": {},
      "attributes": {}
    },
    {
      "label": "MURGHI MASALA 43GX144 (H)",
      "points": [
        [
          957.8947368421051,
          923.6842105263157
        ],
        [
          1025.438596491228,
          923.6842105263157
        ],
        [
          1025.438596491228,
          942.1052631578947
        ],
        [
          957.8947368421051,
          942.1052631578947
        ]
      ],
      "group_id": null,
      "description": "",
      "difficult": false,
      "shape_type": "rectangle",
      "flags": {},
      "attributes": {}
    },
    {
      "label": "MURGHI MASALA 43GX144 (H)",
      "points": [
        [
          960.5263157894735,
          942.1052631578947
        ],
        [
          1028.0701754385964,
          942.1052631578947
        ],
        [
          1028.0701754385964,
          960.5263157894736
        ],
        [
          960.5263157894735,
          960.5263157894736
        ]
      ],
      "group_id": null,
      "description": "",
      "difficult": false,
      "shape_type": "rectangle",
      "flags": {},
      "attributes": {}
    },
    {
      "label": "MURGHI MASALA 43GX144 (H)",
      "points": [
        [
          890.3508771929824,
          954.3859649122807
        ],
        [
          957.8947368421053,
          954.3859649122807
        ],
        [
          957.8947368421053,
          972.8070175438596
        ],
        [
          890.3508771929824,
          972.8070175438596
        ]
      ],
      "group_id": null,
      "description": "",
      "difficult": false,
      "shape_type": "rectangle",
      "flags": {},
      "attributes": {}
    },
    {
      "label": "MURGHI MASALA 43GX144 (H)",
      "points": [
        [
          964.0350877192982,
          964.0350877192982
        ],
        [
          1028.9473684210525,
          964.0350877192982
        ],
        [
          1028.9473684210525,
          978.0701754385964
        ],
        [
          964.0350877192982,
          978.0701754385964
        ]
      ],
      "group_id": null,
      "description": "",
      "difficult": false,
      "shape_type": "rectangle",
      "flags": {},
      "attributes": {}
    },
    {
      "label": "FISH MASALA 80GX72 (H)",
      "points": [
        [
          624.1758241758241,
          1234.065934065934
        ],
        [
          736.2637362637363,
          1234.065934065934
        ],
        [
          736.2637362637363,
          1356.043956043956
        ],
        [
          624.1758241758241,
          1356.043956043956
        ]
      ],
      "group_id": null,
      "description": "",
      "difficult": false,
      "shape_type": "rectangle",
      "flags": {},
      "attributes": {}
    },
    {
      "label": "CHAPLI KABAB 72GX72 (H)",
      "points": [
        [
          825.5721433319314,
          1242.2215170755874
        ],
        [
          909.4875486053689,
          1242.2215170755874
        ],
        [
          909.4875486053689,
          1269.7993368998061
        ],
        [
          825.5721433319314,
          1269.7993368998061
        ]
      ],
      "group_id": null,
      "description": "",
      "difficult": false,
      "shape_type": "rectangle",
      "flags": {},
      "attributes": {}
    },
    {
      "label": "CHAPLI KABAB 72GX72 (H)",
      "points": [
        [
          910.2436761786468,
          1279.4477944478501
        ],
        [
          989.0510948905109,
          1279.4477944478501
        ],
        [
          989.0510948905109,
          1372.2627737226276
        ],
        [
          910.2436761786468,
          1372.2627737226276
        ]
      ],
      "group_id": null,
      "description": "",
      "difficult": false,
      "shape_type": "rectangle",
      "flags": {},
      "attributes": {}
    },
    {
      "label": "CHAPLI KABAB 72GX72 (H)",
      "points": [
        [
          910.2436761786468,
          1245.8711521120838
        ],
        [
          994.1590814520843,
          1245.8711521120838
        ],
        [
          994.1590814520843,
          1273.4489719363025
        ],
        [
          910.2436761786468,
          1273.4489719363025
        ]
      ],
      "group_id": null,
      "description": "",
      "difficult": false,
      "shape_type": "rectangle",
      "flags": {},
      "attributes": {}
    },
    {
      "label": "CHAPLI KABAB 72GX72 (H)",
      "points": [
        [
          910.2436761786468,
          1215.9441448128136
        ],
        [
          994.1590814520843,
          1215.9441448128136
        ],
        [
          994.1590814520843,
          1243.5219646370324
        ],
        [
          910.2436761786468,
          1243.5219646370324
        ]
      ],
      "group_id": null,
      "description": "",
      "difficult": false,
      "shape_type": "rectangle",
      "flags": {},
      "attributes": {}
    },
    {
      "label": "SHAMI KABAB 45GX72 (H)",
      "points": [
        [
          910.2869732710566,
          1160.712272476976
        ],
        [
          989.9186261030878,
          1160.712272476976
        ],
        [
          989.9186261030878,
          1209.4851606605698
        ],
        [
          910.2869732710566,
          1209.4851606605698
        ]
      ],
      "group_id": null,
      "description": null,
      "difficult": false,
      "shape_type": "rectangle",
      "flags": {},
      "attributes": {}
    },
    {
      "label": "SHAMI KABAB 45GX72 (H)",
      "points": [
        [
          824.885513417042,
          1273.1210316010636
        ],
        [
          908.0291970802919,
          1273.1210316010636
        ],
        [
          908.0291970802919,
          1370.0729927007299
        ],
        [
          824.885513417042,
          1370.0729927007299
        ]
      ],
      "group_id": null,
      "description": null,
      "difficult": false,
      "shape_type": "rectangle",
      "flags": {},
      "attributes": {}
    },
    {
      "label": "KOFTA MASALA 43GX144 (H)",
      "points": [
        [
          999.2947710691578,
          1280.9076484624488
        ],
        [
          1078.102189781022,
          1280.9076484624488
        ],
        [
          1078.102189781022,
          1373.7226277372263
        ],
        [
          999.2947710691578,
          1373.7226277372263
        ]
      ],
      "group_id": null,
      "description": "",
      "difficult": false,
      "shape_type": "rectangle",
      "flags": {},
      "attributes": {}
    },
    {
      "label": "KOFTA MASALA 43GX144 (H)",
      "points": [
        [
          997.8349170545594,
          1252.5547445255474
        ],
        [
          1076.6423357664232,
          1252.5547445255474
        ],
        [
          1076.6423357664232,
          1278.102189781022
        ],
        [
          997.8349170545594,
          1278.102189781022
        ]
      ],
      "group_id": null,
      "description": "",
      "difficult": false,
      "shape_type": "rectangle",
      "flags": {},
      "attributes": {}
    },
    {
      "label": "KOFTA MASALA 43GX144 (H)",
      "points": [
        [
          997.1049900472601,
          1227.7372262773724
        ],
        [
          1075.912408759124,
          1227.7372262773724
        ],
        [
          1075.912408759124,
          1253.284671532847
        ],
        [
          997.1049900472601,
          1253.284671532847
        ]
      ],
      "group_id": null,
      "description": "",
      "difficult": false,
      "shape_type": "rectangle",
      "flags": {},
      "attributes": {}
    },
    {
      "label": "KOFTA MASALA 43GX144 (H)",
      "points": [
        [
          994.9152090253624,
          1200.0000000000002
        ],
        [
          1073.7226277372263,
          1200.0000000000002
        ],
        [
          1073.7226277372263,
          1225.5474452554747
        ],
        [
          994.9152090253624,
          1225.5474452554747
        ]
      ],
      "group_id": null,
      "description": "",
      "difficult": false,
      "shape_type": "rectangle",
      "flags": {},
      "attributes": {}
    },
    {
      "label": "Delhi Nihari 50GM (KK)",
      "points": [
        [
          726.6683959960938,
          707.5
        ],
        [
          788.75,
          707.5
        ],
        [
          788.75,
          723.8507080078125
        ],
        [
          726.6683959960938,
          723.8507080078125
        ]
      ],
      "group_id": null,
      "description": null,
      "difficult": false,
      "shape_type": "rectangle",
      "flags": {},
      "attributes": {}
    },
    {
      "label": "Delhi Nihari 50GM (KK)",
      "points": [
        [
          727.9183959960938,
          690.625
        ],
        [
          790.0,
          690.625
        ],
        [
          790.0,
          706.9757080078125
        ],
        [
          727.9183959960938,
          706.9757080078125
        ]
      ],
      "group_id": null,
      "description": null,
      "difficult": false,
      "shape_type": "rectangle",
      "flags": {},
      "attributes": {}
    }
  ],
  "imagePath": "questionImage_2474_91060_7_-1_9_-1.jpg",
  "imageData": null,
  "imageHeight": 1600,
  "imageWidth": 1600,
  "text": ""
}